detecty/bbox.py
detecty/model.ckpt
detecty/model.py
detecty/util.py
detecty/version.py
detecty-0.0.31.dist-info/METADATA
detecty-0.0.31.dist-info/WHEEL
detecty-0.0.31.dist-info/entry_points.txt
detecty-0.0.31.dist-info/RECORD
